{
    "cache_scenarios": [
        {
            "scenario": "Valid Cache",
            "ttl": 15,
            "weather_state": "Light Rain",
            "cache_created_time": "2026-06-17T14:00:00Z"
        },
        {
            "scenario": "Expired Cache",
            "ttl": 35,
            "weather_state": "Clear Weather",
            "cache_created_time": "2026-06-17T13:30:00Z"
        },
        {
            "scenario": "Cache TTL = 29",
            "ttl": 29,
            "weather_state": "Moderate Rain",
            "cache_created_time": "2026-06-17T13:56:46Z"
        },
        {
            "scenario": "Cache TTL = 30",
            "ttl": 30,
            "weather_state": "Heavy Rain",
            "cache_created_time": "2026-06-17T13:55:46Z"
        },
        {
            "scenario": "Cache TTL = 31",
            "ttl": 31,
            "weather_state": "Extreme Rain",
            "cache_created_time": "2026-06-17T13:54:46Z"
        }
    ],
    "used_by": [
        "TS_RS_021",
        "TS_RS_022",
        "TS_RS_023",
        "TS_RS_API_010",
        "TS_RS_API_011",
        "TS_RS_E2E_003",
        "TS_RS_E2E_005",
        "TS_RS_E2E_009"
    ]
}